{
  "metadata": {
    "id": "urn:bbc:ares::index:bengali/53988070/desktop/domestic",
    "locators": {
      "assetUri": "/bengali/53988070",
      "cpsUrn": "urn:bbc:content:assetUri:bengali/53988070",
      "curie": "http://www.bbc.co.uk/asset/50632633-a12c-40da-bdb8-38095fa2b390/desktop/domestic",
      "assetId": "53988070"
    },
    "type": "FIX",
    "createdBy": "bengali-v6",
    "language": "bn",
    "lastUpdated": 1600102154284,
    "firstPublished": 1598975756000,
    "lastPublished": 1600102148000,
    "timestamp": 1600102147000,
    "options": {
      "allowAdvertising": true
    },
    "analyticsLabels": {
      "cps_asset_type": "fix",
      "counterName": "bengali.feature_index.53988070.page",
      "cps_asset_id": "53988070"
    },
    "tags": {},
    "version": "v1.3.6",
    "blockTypes": [
      "lead-feature-now",
      "container-top-stories",
      "av-stories-now",
      "other-top-stories",
      "feature-digest"
    ],
    "title": "যুক্তরাষ্ট্র নির্বাচন ২০২০",
    "summary": "মার্কিন নির্বাচন সম্পর্কিত নানা ধরনের খবর, বিশ্লেষণ এবং ছবি রয়েছে এখানে।",
    "atiAnalytics": {
      "producerName": "BENGALI",
      "producerId": "31"
    }
  },
  "content": {
    "groups": [
      {
        "type": "lead-feature-now",
        "title": "Lead Feature",
        "items": [
          {
            "headlines": {
              "headline": "যুক্তরাষ্ট্র নির্বাচন ২০২০: কে এগিয়ে- ট্রাম্প না বাইডেন?",
              "overtyped": "জনমত জরিপে কে এগিয়ে - ট্রাম্প না বাইডেন?"
            },
            "locators": {
              "assetUri": "/bengali/news-53685000",
              "cpsUrn": "urn:bbc:content:assetUri:bengali/news-53685000",
              "curie": "http://www.bbc.co.uk/asset/5573b032-30b6-4acc-b320-8f034cb127a5",
              "assetId": "53685000"
            },
            "summary": "আমেরিকার ভোটাররা ৩রা নভেম্বর নির্ধারণ করবেন ডোনাল্ড ট্রাম্পকে তারা আরো চার বছরের জন্য হোয়াইট হাউজে দেখতে চান কিনা। এখানে ২০১৬ সালের নির্বাচনের সঙ্গে একটি তুলনামূলক বিশ্লেষণ তুলে ধরা হলো।",
            "timestamp": 1596730284000,
            "language": "bn",
            "passport": {
              "category": {
                "categoryId": "http://www.bbc.co.uk/ontologies/applicationlogic-news/Analysis",
                "categoryName": "Analysis"
              },
              "campaigns": [
                {
                  "campaignId": "5a988e3739461b000e9dabfa",
                  "campaignName": "WS - Give me perspective"
                }
              ],
              "taggings": []
            },
            "cpsType": "STY",
            "indexImage": {
              "id": "113940846",
              "subType": "index",
              "href": "http://c.files.bbci.co.uk/FD24/production/_113940846_index_promo_poll_tracker_bw_976.png",
              "path": "/cpsprodpb/FD24/production/_113940846_index_promo_poll_tracker_bw_976.png",
              "height": 549,
              "width": 976,
              "altText": "নির্বাচনী লড়াইয়ে মুখোমুখী ডোনাল্ড ট্রাম্প এবং জো বাইডেন।",
              "caption": "নির্বাচনী লড়াইয়ে মুখোমুখী ডোনাল্ড ট্রাম্প এবং জো বাইডেন।",
              "copyrightHolder": "BBC",
              "type": "image"
            },
            "options": {
              "isBreakingNews": false,
              "isFactCheck": false
            },
            "id": "urn:bbc:ares::asset:bengali/news-53685000",
            "type": "cps"
          }
        ],
        "semanticGroupName": "Lead Feature"
      },
      {
        "type": "container-top-stories",
        "title": "Container Top Stories",
        "items": [
          {
            "headlines": {
              "headline": "যুক্তরাষ্ট্রে তিক্ততা, বিভাজন আর আক্রমণের নির্বাচন"
            },
            "locators": {
              "assetUri": "/bengali/news-54045613",
              "cpsUrn": "urn:bbc:content:assetUri:bengali/news-54045613",
              "curie": "http://www.bbc.co.uk/asset/662453cc-af23-4b89-82d3-6a614c0da5dd",
              "assetId": "54045613"
            },
            "summary": "বলা হচ্ছে কাছাকাছি সময়ে কোন মার্কিন নির্বাচনে এত উস্কানি, নোংরামি, তিক্ততা ও সামাজিক বিভাজন দেখা যায়নি।",
            "timestamp": 1599373161000,
            "language": "bn",
            "byline": {
              "name": "শাহনাজ পারভীন",
              "title": "বিবিসি বাংলা",
              "persons": [
                {
                  "name": "শাহনাজ পারভীন",
                  "function": "বিবিসি বাংলা, ঢাকা"
                }
              ]
            },
            "passport": {
              "category": {
                "categoryId": "http://www.bbc.co.uk/ontologies/applicationlogic-news/News",
                "categoryName": "News"
              },
              "campaigns": [
                {
                  "campaignId": "5a988e3739461b000e9dabfa",
                  "campaignName": "WS - Give me perspective"
                }
              ],
              "taggings": []
            },
            "cpsType": "STY",
            "indexImage": {
              "id": "114259703",
              "subType": "index",
              "href": "http://c.files.bbci.co.uk/784B/production/_114259703_blah.jpg",
              "path": "/cpsprodpb/784B/production/_114259703_blah.jpg",
              "height": 549,
              "width": 976,
              "altText": "ট্রাম্প ও বাইডেন",
              "caption": "মনোনয়নের পর থেকেই একে অপরকে উস্কানি দিচ্ছে দুই প্রতিদ্বন্দ্বী",
              "copyrightHolder": "BBC",
              "type": "image"
            },
            "options": {
              "isBreakingNews": false,
              "isFactCheck": false
            },
            "id": "urn:bbc:ares::asset:bengali/news-54045613",
            "type": "cps"
          },
          {
            "headlines": {
              "headline": "যুক্তরাষ্ট্রের নির্বাচন যেভাবে অন্য দেশের তুলনায় একেবারেই ভিন্ন"
            },
            "locators": {
              "assetUri": "/bengali/news-53788641",
              "cpsUrn": "urn:bbc:content:assetUri:bengali/news-53788641",
              "curie": "http://www.bbc.co.uk/asset/892777a1-3f50-4aec-b37b-751e35cc02df",
              "assetId": "53788641"
            },
            "summary": "যুক্তরাষ্ট্রের নির্বাচনের পদ্ধতি অনেক দেশের তুলনায় ভিন্ন এবং কারো কাছে একটু জটিল মনে হতে পারে। এখানে খুব সহজভাবে এই পদ্ধতির মূল দিকগুলো তুলে ধরার চেষ্টা করা হলো।",
            "timestamp": 1597480519000,
            "language": "bn",
            "passport": {
              "category": {
                "categoryId": "http://www.bbc.co.uk/ontologies/applicationlogic-news/News",
                "categoryName": "News"
              },
              "campaigns": [
                {
                  "campaignId": "5a988e2939461b000e9dabf8",
                  "campaignName": "WS - Educate me"
                }
              ],
              "taggings": []
            },
            "cpsType": "STY",
            "indexImage": {
              "id": "114367709",
              "subType": "index",
              "href": "http://c.files.bbci.co.uk/16298/production/_114367709_gettyimages-1228480094.jpg",
              "path": "/cpsprodpb/16298/production/_114367709_gettyimages-1228480094.jpg",
              "height": 549,
              "width": 976,
              "altText": "ব্যালট বাক্স",
              "copyrightHolder": "CHRIS DELMAS",
              "type": "image"
            },
            "options": {
              "isBreakingNews": false,
              "isFactCheck": false
            },
            "id": "urn:bbc:ares::asset:bengali/news-53788641",
            "type": "cps"
          },
          {
            "headlines": {
              "headline": "যুক্তরাষ্ট্র নির্বাচন ২০২০: ইলেকটোরাল কলেজ পদ্ধতি কী ও কীভাবে কাজ করে",
              "overtyped": "ইলেকটোরাল কলেজ পদ্ধতি কী ও কীভাবে কাজ করে"
            },
            "locators": {
              "assetUri": "/bengali/news-53814316",
              "cpsUrn": "urn:bbc:content:assetUri:bengali/news-53814316",
              "curie": "http://www.bbc.co.uk/asset/037ce119-99bb-4815-9503-b24838883d5b",
              "assetId": "53814316"
            },
            "summary": "যুক্তরাষ্ট্রে গত পাঁচটি নির্বাচনের মধ্যে দুটোতেই কম পপুলার ভোট পেয়েও ইলেকটোরাল কলেজ পদ্ধতিতে ডোনাল্ড ট্রাম্প ও জর্জ বুশ প্রেসিডেন্ট নির্বাচিত হয়েছেন।",
            "timestamp": 1597745708000,
            "language": "bn",
            "passport": {
              "category": {
                "categoryId": "http://www.bbc.co.uk/ontologies/applicationlogic-news/Explainer",
                "categoryName": "Explainer"
              },
              "campaigns": [
                {
                  "campaignId": "5a988e3739461b000e9dabfa",
                  "campaignName": "WS - Give me perspective"
                }
              ],
              "taggings": []
            },
            "cpsType": "STY",
            "indexImage": {
              "id": "114004523",
              "subType": "index",
              "href": "http://c.files.bbci.co.uk/7F1C/production/_114004523_gettyimages-74065773.jpg",
              "path": "/cpsprodpb/7F1C/production/_114004523_gettyimages-74065773.jpg",
              "height": 549,
              "width": 976,
              "altText": "যুক্তরাষ্ট্রে বেশি ভোট পেলেই যে একজন প্রার্থী সবসময় প্রেসিডেন্ট নির্বাচিত হবেন তা নয়।",
              "caption": "যুক্তরাষ্ট্রে বেশি ভোট পেলেই যে একজন প্রার্থী সবসময় প্রেসিডেন্ট নির্বাচিত হবেন তা নয়।",
              "copyrightHolder": "Getty Images",
              "type": "image"
            },
            "options": {
              "isBreakingNews": false,
              "isFactCheck": false
            },
            "id": "urn:bbc:ares::asset:bengali/news-53814316",
            "type": "cps"
          },
          {
            "headlines": {
              "headline": "যুক্তরাষ্ট্রে প্রেসিডেন্ট নির্বাচনে জেতার চাবিকাঠি কোন রাজ্যগুলোতে",
              "overtyped": "নির্বাচনে জেতার চাবিকাঠি কোন রাজ্যগুলোতে"
            },
            "locators": {
              "assetUri": "/bengali/news-53794009",
              "cpsUrn": "urn:bbc:content:assetUri:bengali/news-53794009",
              "curie": "http://www.bbc.co.uk/asset/3990ec2a-06e6-4b16-8127-e9296d9a7afa",
              "assetId": "53794009"
            },
            "summary": "আমেরিকার প্রেসিডেন্ট নির্বাচনে জয় পরাজয় নির্ধারিত হয় মূলত বিশেষ কিছু রাজ্যের ভোট কোন প্রার্থী পেলেন তার ওপর। তাই মূল প্রতিদ্বন্দ্বিতা এই রাজ্যগুলোতেই - যেগুলোকে বলে 'ব্যাটলগ্রাউণ্ড' স্টেট।",
            "timestamp": 1597546523000,
            "language": "bn",
            "passport": {
              "category": {
                "categoryId": "http://www.bbc.co.uk/ontologies/applicationlogic-news/Explainer",
                "categoryName": "Explainer"
              },
              "campaigns": [
                {
                  "campaignId": "5a988e3e39461b000e9dabfb",
                  "campaignName": "WS - Keep me on trend"
                }
              ],
              "taggings": []
            },
            "cpsType": "STY",
            "indexImage": {
              "id": "113954693",
              "subType": "index",
              "href": "http://c.files.bbci.co.uk/9ADD/production/_113954693__113666169_usvoter.jpg",
              "path": "/cpsprodpb/9ADD/production/_113954693__113666169_usvoter.jpg",
              "height": 549,
              "width": 976,
              "altText": "আমেরিকার একজন ভোটার",
              "caption": "আমেরিকায় প্রেসিডেন্ট নির্বাচন তেসরা নভেম্বর",
              "copyrightHolder": "Getty Images",
              "type": "image"
            },
            "options": {
              "isBreakingNews": false,
              "isFactCheck": false
            },
            "id": "urn:bbc:ares::asset:bengali/news-53794009",
            "type": "cps"
          },
          {
            "headlines": {
              "headline": "ডোনাল্ড ট্রাম্প: টিভি তারকা থেকে আমেরিকান প্রেসিডেন্ট"
            },
            "locators": {
              "assetUri": "/bengali/news-53991373",
              "cpsUrn": "urn:bbc:content:assetUri:bengali/news-53991373",
              "curie": "http://www.bbc.co.uk/asset/45cafa7e-b9e1-4bf6-923f-593f9ca65301",
              "assetId": "53991373"
            },
            "summary": "রিয়েল এস্টেট ব্যবসায়ী থেকে বিনোদন জগতের তারকা। হয়েছেন পৃথিবীর সবচেয়ে ক্ষমতাধর প্রেসিডেন্ট। তার বিরুদ্ধে অভিযোগের যেমন শেষ নেই তেমনি রয়েছে তার ব্যপক জনপ্রিয়তা।",
            "timestamp": 1599126885000,
            "language": "bn",
            "passport": {
              "category": {
                "categoryId": "http://www.bbc.co.uk/ontologies/applicationlogic-news/Feature",
                "categoryName": "Feature"
              },
              "campaigns": [
                {
                  "campaignId": "5a988e2939461b000e9dabf8",
                  "campaignName": "WS - Educate me"
                }
              ],
              "taggings": []
            },
            "cpsType": "STY",
            "indexImage": {
              "id": "114203304",
              "subType": "index",
              "href": "http://c.files.bbci.co.uk/9D8A/production/_114203304_7b8d29d0-53b4-4128-b8fb-78193c8805c2.jpg",
              "path": "/cpsprodpb/9D8A/production/_114203304_7b8d29d0-53b4-4128-b8fb-78193c8805c2.jpg",
              "height": 549,
              "width": 976,
              "altText": "ডোনাল্ড ট্রাম্প",
              "copyrightHolder": "BBC",
              "type": "image"
            },
            "options": {
              "isBreakingNews": false,
              "isFactCheck": false
            },
            "id": "urn:bbc:ares::asset:bengali/news-53991373",
            "type": "cps"
          },
          {
            "headlines": {
              "headline": "জো বাইডেন: এবারের দৌড় হোয়াইট হাউসের জন্য"
            },
            "locators": {
              "assetUri": "/bengali/news-53874490",
              "cpsUrn": "urn:bbc:content:assetUri:bengali/news-53874490",
              "curie": "http://www.bbc.co.uk/asset/562361c9-1aad-44e4-bb45-a645e51e1cc8",
              "assetId": "53874490"
            },
            "summary": "প্রায় ৫০ বছরের রাজনৈতিক ক্যারিয়ারে প্রেসিডেন্ট পদে জেতার জন্য তৃতীয়বারের প্রচেষ্টা এবং দীর্ঘ চল্লিশ বছরের স্বপ্ন পূরণের লড়াই ডেমোক্র্যাট দলের প্রার্থী জো বাইডেনের।",
            "timestamp": 1598147785000,
            "language": "bn",
            "passport": {
              "category": {
                "categoryId": "http://www.bbc.co.uk/ontologies/applicationlogic-news/Explainer",
                "categoryName": "Explainer"
              },
              "campaigns": [
                {
                  "campaignId": "5a988e3e39461b000e9dabfb",
                  "campaignName": "WS - Keep me on trend"
                }
              ],
              "taggings": []
            },
            "cpsType": "STY",
            "indexImage": {
              "id": "114063465",
              "subType": "index",
              "href": "http://c.files.bbci.co.uk/DC74/production/_114063465_biden_640-nc.png",
              "path": "/cpsprodpb/DC74/production/_114063465_biden_640-nc.png",
              "height": 549,
              "width": 976,
              "altText": "জো বাইডেন",
              "copyrightHolder": "BBC",
              "type": "image"
            },
            "options": {
              "isBreakingNews": false,
              "isFactCheck": false
            },
            "id": "urn:bbc:ares::asset:bengali/news-53874490",
            "type": "cps"
          },
          {
            "headlines": {
              "headline": "ট্রাম্প দেশকে 'বিভক্ত করেছেন' - বাইডেন ও তার রানিং মেট কমালা"
            },
            "locators": {
              "assetUri": "/bengali/news-53761305",
              "cpsUrn": "urn:bbc:content:assetUri:bengali/news-53761305",
              "curie": "http://www.bbc.co.uk/asset/bed8b29a-6cfa-463c-a431-3ab2488b5649",
              "assetId": "53761305"
            },
            "summary": "জো বাইডেন এবং তার রানিং মেট কমালা হ্যারিস, প্রেসিডেন্ট ডোনাল্ড ট্রাম্পকে একজন অযোগ্য নেতা হিসেবে মন্তব্য করেছেন। ট্রাম্পও এর জবাব দিতে ছাড়েননি।",
            "timestamp": 1597294513000,
            "language": "bn",
            "passport": {
              "category": {
                "categoryId": "http://www.bbc.co.uk/ontologies/applicationlogic-news/News",
                "categoryName": "News"
              },
              "campaigns": [
                {
                  "campaignId": "5a988e4739461b000e9dabfc",
                  "campaignName": "WS - Update me"
                }
              ],
              "taggings": []
            },
            "cpsType": "STY",
            "indexImage": {
              "id": "113917772",
              "subType": "index",
              "href": "http://c.files.bbci.co.uk/6C7B/production/_113917772_062888947.jpg",
              "path": "/cpsprodpb/6C7B/production/_113917772_062888947.jpg",
              "height": 549,
              "width": 976,
              "altText": "কামালা হ্যারিস এবং জো বাইডেন",
              "caption": "কামালা হ্যারিস এবং জো বাইডেন উইলমিংটনের নির্বাচনী প্রচারণায় একসঙ্গে যোগ দেন।",
              "copyrightHolder": "Reuters",
              "type": "image"
            },
            "options": {
              "isBreakingNews": false,
              "isFactCheck": false
            },
            "id": "urn:bbc:ares::asset:bengali/news-53761305",
            "type": "cps"
          },
          {
            "headlines": {
              "headline": "প্রেসিডেন্ট ট্রাম্পকে নিয়ে দশটি মারাত্মক দাবি"
            },
            "locators": {
              "assetUri": "/bengali/news-53108194",
              "cpsUrn": "urn:bbc:content:assetUri:bengali/news-53108194",
              "curie": "http://www.bbc.co.uk/asset/df12033a-8216-46c8-a5bd-0a6e38de06e4",
              "assetId": "53108194"
            },
            "summary": "মি. ট্রাম্পের সাবেক জাতীয় নিরাপত্তা উপদেষ্টা জন বোল্টন তার বইয়ে প্রেসিডেন্ট সম্পর্কে মারাত্মক কিছু মন্তব্য করেছেন। হোয়াইট হাউস এই বইয়ের প্রকাশ বন্ধ করতে উঠেপড়ে লেগেছে।",
            "timestamp": 1592584023000,
            "language": "bn",
            "passport": {
              "category": {
                "categoryId": "http://www.bbc.co.uk/ontologies/applicationlogic-news/Explainer",
                "categoryName": "Explainer"
              },
              "campaigns": [
                {
                  "campaignId": "5a988e3739461b000e9dabfa",
                  "campaignName": "WS - Give me perspective"
                }
              ],
              "taggings": []
            },
            "cpsType": "STY",
            "indexImage": {
              "id": "112959623",
              "subType": "index",
              "href": "http://c.files.bbci.co.uk/7FB7/production/_112959623_mediaitem112959622.jpg",
              "path": "/cpsprodpb/7FB7/production/_112959623_mediaitem112959622.jpg",
              "height": 549,
              "width": 976,
              "altText": "জন বোল্টন তাকিয়ে আছেন মি. ট্রাম্পের দিকে",
              "caption": "প্রে. ট্রাম্পের প্রশাসনে কাজের অভিজ্ঞতা নিয়ে সর্বসাম্প্রতিক বইটির লেখক সাবেক আমেরিকান কর্মকর্তা জন বোল্টন",
              "copyrightHolder": "AFP",
              "type": "image"
            },
            "options": {
              "isBreakingNews": false,
              "isFactCheck": false
            },
            "id": "urn:bbc:ares::asset:bengali/news-53108194",
            "type": "cps"
          },
          {
            "headlines": {
              "headline": "কমালা হ্যারিসকে ঘিরে এখন যেসব ষড়যন্ত্র তত্ত্ব ছড়ানো হচ্ছে"
            },
            "locators": {
              "assetUri": "/bengali/news-53849742",
              "cpsUrn": "urn:bbc:content:assetUri:bengali/news-53849742",
              "curie": "http://www.bbc.co.uk/asset/5fa4400c-fc93-431e-8a2d-467d6d288460",
              "assetId": "53849742"
            },
            "summary": "মার্কিন নির্বাচনে ডেমোক্রেটিক দলের ভাইস-প্রেসিডেন্ট পদপ্রার্থী সামাজিক মাধ্যমে নানা ধরনের ষড়যন্ত্র তত্ত্বের শিকার হয়েছেন। কী পেয়েছে বিবিসি তার অনুসন্ধানে?",
            "timestamp": 1598003558000,
            "language": "bn",
            "byline": {
              "name": "জ্যাক  গুডম্যান",
              "title": "বিবিসি রিয়ালিটি চেক",
              "persons": [
                {
                  "name": "জ্যাক গুডম্যান",
                  "function": "বিবিসি রিয়ালিটি চেক"
                }
              ]
            },
            "passport": {
              "category": {
                "categoryId": "http://www.bbc.co.uk/ontologies/applicationlogic-news/FactCheck",
                "categoryName": "Fact Check"
              },
              "campaigns": [
                {
                  "campaignId": "5a988e3e39461b000e9dabfb",
                  "campaignName": "WS - Keep me on trend"
                }
              ],
              "taggings": []
            },
            "cpsType": "STY",
            "indexImage": {
              "id": "114016487",
              "subType": "index",
              "href": "http://c.files.bbci.co.uk/1327D/production/_114016487_harrisk_reuters2.jpg",
              "path": "/cpsprodpb/1327D/production/_114016487_harrisk_reuters2.jpg",
              "height": 549,
              "width": 976,
              "altText": "কামালা হ্যারিস",
              "copyrightHolder": "Reuters",
              "type": "image"
            },
            "options": {
              "isBreakingNews": false,
              "isFactCheck": false
            },
            "id": "urn:bbc:ares::asset:bengali/news-53849742",
            "type": "cps"
          }
        ],
        "semanticGroupName": "Container Top Stories"
      },
      {
        "type": "av-stories-now",
        "title": "Watch/Listen",
        "items": [
          {
            "headlines": {
              "headline": "ট্রাম্প-বাইডেন: নীতিগত তফাৎ আর সেখানকার বাংলাদেশিদের পছন্দ"
            },
            "locators": {
              "assetUri": "/bengali/news-53813339",
              "cpsUrn": "urn:bbc:content:assetUri:bengali/news-53813339",
              "curie": "http://www.bbc.co.uk/asset/4b6a2841-7082-47f4-bfd7-d221e21a2e61",
              "assetId": "53813339"
            },
            "summary": "নভেম্বরে যুক্তরাষ্ট্রের নির্বাচনে প্রতিদ্বন্দ্বী দুই দল রিপাবলিকান ও ডেমোক্রেটিক পার্টি'র কে কী নিয়ে আসছেন, তা নিয়ে এখন বৈশ্বিক রাজনীতিতে চলছে নানা আলোচনা।",
            "timestamp": 1597816444000,
            "language": "bn",
            "passport": {
              "category": {
                "categoryId": "http://www.bbc.co.uk/ontologies/applicationlogic-news/News",
                "categoryName": "News"
              },
              "campaigns": [
                {
                  "campaignId": "5a988e3739461b000e9dabfa",
                  "campaignName": "WS - Give me perspective"
                }
              ],
              "taggings": []
            },
            "cpsType": "MAP",
            "media": {
              "id": "p08nvvvh",
              "subType": "clip",
              "format": "video",
              "title": "ট্রাম্প-বাইডেন: নীতিগত তফাৎ আর সেখানকার বাংলাদেশিদের পছন্দ",
              "synopses": {
                "short": "যুক্তরাষ্ট্রের নির্বাচনে ট্রাম্প আর বাইডেনের নীতি বিবেচনায় প্রবাসী বাংলাদেশীদেরা কাকে চায়?"
              },
              "imageUrl": "ichef.bbci.co.uk/images/ic/$recipe/p08nwcfm.jpg",
              "embedding": true,
              "advertising": true,
              "caption": "যুক্তরাষ্ট্রের নির্বাচনে ট্রাম্প আর বাইডেনের নীতি বিবেচনায় প্রবাসী বাংলাদেশীদেরা কাকে চায়?",
              "versions": [
                {
                  "versionId": "p08nvvvl",
                  "types": [
                    "Original"
                  ],
                  "duration": 223,
                  "durationISO8601": "PT3M43S",
                  "warnings": {},
                  "availableTerritories": {
                    "uk": true,
                    "nonUk": true
                  },
                  "availableFrom": 1597675727000
                }
              ],
              "imageCopyright": "BBC",
              "smpKind": "programme",
              "type": "media"
            },
            "indexImage": {
              "id": "113978058",
              "subType": "index",
              "href": "http://c.files.bbci.co.uk/14C5F/production/_113978058_p08nwcfm.jpg",
              "path": "/cpsprodpb/14C5F/production/_113978058_p08nwcfm.jpg",
              "height": 549,
              "width": 976,
              "altText": "বিভিন্ন বিবেচনায় যুক্তরাষ্ট্র প্রবাসী বাংলাদেশীদেরই বা কোন দল পছন্দ?",
              "caption": "বিভিন্ন বিবেচনায় যুক্তরাষ্ট্র প্রবাসী বাংলাদেশীদেরই বা কোন দল পছন্দ?",
              "copyrightHolder": "BBC",
              "type": "image"
            },
            "options": {
              "isBreakingNews": false,
              "isFactCheck": false
            },
            "id": "urn:bbc:ares::asset:bengali/news-53813339",
            "type": "cps"
          }
        ],
        "semanticGroupName": "Watch/Listen"
      },
      {
        "type": "other-top-stories",
        "title": "Standalone Other Top Stories",
        "items": [
          {
            "headlines": {
              "headline": "চীন চায় ট্রাম্প হেরে যাক, রাশিয়া বাইডেনকে বিপদে ফেলতে উন্মুখ: গোয়েন্দা রিপোর্ট"
            },
            "locators": {
              "assetUri": "/bengali/news-53708148",
              "cpsUrn": "urn:bbc:content:assetUri:bengali/news-53708148",
              "curie": "http://www.bbc.co.uk/asset/cd19105d-99cb-4afe-9cbf-734360bc495a",
              "assetId": "53708148"
            },
            "summary": "যুক্তরাষ্ট্রের যে বিভাগটি বিদেশি গুপ্তচরবৃত্তি ঠেকানোর কাজ করে তারা বলছে চীন, রাশিয়া এবং ইরানসহ আরো কয়েকটি দেশ নভেম্বরে প্রেসিডেন্ট নির্বাচনকে প্রভাবিত করার কাজে নেমে পড়েছে।",
            "timestamp": 1596898480000,
            "language": "bn",
            "passport": {
              "category": {
                "categoryId": "http://www.bbc.co.uk/ontologies/applicationlogic-news/News",
                "categoryName": "News"
              },
              "campaigns": [
                {
                  "campaignId": "5a988e4739461b000e9dabfc",
                  "campaignName": "WS - Update me"
                }
              ],
              "taggings": []
            },
            "cpsType": "STY",
            "indexImage": {
              "id": "113860593",
              "subType": "index",
              "href": "http://c.files.bbci.co.uk/9A52/production/_113860593_53708148.jpg",
              "path": "/cpsprodpb/9A52/production/_113860593_53708148.jpg",
              "height": 350,
              "width": 623,
              "altText": "মার্কিন কাউন্টার-ইন্টেলিজেন্স বিভাগের প্রধান উইলিয়াম ইভানিনা। তিনি বলেছেন, চীন চাইছেনা ডোনাল্ড ট্রাম্প আবারো জয়ী হন এবং রাশিয়া জো বাইডেনের পেছনে লেগেছে",
              "caption": "মার্কিন কাউন্টার-ইন্টেলিজেন্স বিভাগের প্রধান উইলিয়াম ইভানিনা। তিনি বলেছেন, চীন চাইছেনা ডোনাল্ড ট্রাম্প আবারো জয়ী হন এবং রাশিয়া জো বাইডেনের পেছনে লেগেছে",
              "copyrightHolder": "Gettys",
              "type": "image"
            },
            "options": {
              "isBreakingNews": false,
              "isFactCheck": false
            },
            "id": "urn:bbc:ares::asset:bengali/news-53708148",
            "type": "cps"
          },
          {
            "headlines": {
              "headline": "ইভাঙ্কা ট্রাম্পকে নিয়ে কেন এতো মাতামাতি?"
            },
            "locators": {
              "assetUri": "/bengali/news-54063579",
              "cpsUrn": "urn:bbc:content:assetUri:bengali/news-54063579",
              "curie": "http://www.bbc.co.uk/asset/a4bfb778-9cd2-499a-a40b-dc21e6289826",
              "assetId": "54063579"
            },
            "summary": "যুক্তরাষ্ট্রে ফার্স্ট লেডি মেলানিয়া ট্রাম্পের চাইতেও বেশি আলোচিত তার সৎ কন্যা ইভাঙ্কা ট্রাম্প। হোয়াইট হাউজে প্রেসিডেন্ট ট্রাম্পের বিশ্বস্ত একজন উপদেষ্টা হিসেবে কাজ করছেন তিনি। কেন তাকে নিয়ে এতো আলোচনা?",
            "timestamp": 1599531831000,
            "language": "bn",
            "passport": {
              "category": {
                "categoryId": "http://www.bbc.co.uk/ontologies/applicationlogic-news/Explainer",
                "categoryName": "Explainer"
              },
              "campaigns": [
                {
                  "campaignId": "5a988e3739461b000e9dabfa",
                  "campaignName": "WS - Give me perspective"
                }
              ],
              "taggings": []
            },
            "cpsType": "STY",
            "indexImage": {
              "id": "114274706",
              "subType": "index",
              "href": "http://c.files.bbci.co.uk/ED4B/production/_114274706_1b1af071-2570-48b8-923c-6470e3a0a02d.jpg",
              "path": "/cpsprodpb/ED4B/production/_114274706_1b1af071-2570-48b8-923c-6470e3a0a02d.jpg",
              "height": 549,
              "width": 976,
              "altText": "কন্যা ইভাঙ্কার সঙ্গে প্রেসিডেন্ট ট্রাম্প।",
              "caption": "হোয়াইট হাউজের সভাতেও প্রেসিডেন্ট ট্রাম্প অনেক সময় ইভাঙ্কা ট্রাম্পকে বেবি বলে ডাকেন।",
              "copyrightHolder": "AFP",
              "type": "image"
            },
            "options": {
              "isBreakingNews": false,
              "isFactCheck": false
            },
            "id": "urn:bbc:ares::asset:bengali/news-54063579",
            "type": "cps"
          },
          {
            "headlines": {
              "headline": "অরেগনের সহিংসতা নিয়ে ডোনাল্ড ট্রাম্প ও জো বাইডেনের বাকযুদ্ধ"
            },
            "locators": {
              "assetUri": "/bengali/news-53971498",
              "cpsUrn": "urn:bbc:content:assetUri:bengali/news-53971498",
              "curie": "http://www.bbc.co.uk/asset/2d5b9c56-d404-4f61-91a3-808ee27b1f81",
              "assetId": "53971498"
            },
            "summary": "নিজের শহরে 'মৃত্যু এবং ধ্বংসলীলা' চালাতে দেয়ার জন্য পোর্টল্যান্ডের ডেমোক্রেটিক মেয়র টেড হোয়েলারকে দায়ী করেছেন ডোনাল্ড ট্রাম্প। জো বাইডেন বলেছেন, 'বেপরোয়াভাবে সহিংসতায় উস্কানি দিয়েছেন' মি. ট্রাম্প।",
            "timestamp": 1598857101000,
            "language": "bn",
            "passport": {
              "category": {
                "categoryId": "http://www.bbc.co.uk/ontologies/applicationlogic-news/News",
                "categoryName": "News"
              },
              "campaigns": [
                {
                  "campaignId": "5a988e4739461b000e9dabfc",
                  "campaignName": "WS - Update me"
                }
              ],
              "taggings": []
            },
            "cpsType": "STY",
            "indexImage": {
              "id": "114184665",
              "subType": "index",
              "href": "http://c.files.bbci.co.uk/DD48/production/_114184665_6f56aa1a-6433-4816-8716-369549dfa826.jpg",
              "path": "/cpsprodpb/DD48/production/_114184665_6f56aa1a-6433-4816-8716-369549dfa826.jpg",
              "height": 549,
              "width": 976,
              "altText": "জো বাইডেন এবং ডোনাল্ড ট্রাম্প",
              "caption": "জো বাইডেন এবং ডোনাল্ড ট্রাম্প",
              "copyrightHolder": "BBC",
              "type": "image"
            },
            "options": {
              "isBreakingNews": false,
              "isFactCheck": false
            },
            "id": "urn:bbc:ares::asset:bengali/news-53971498",
            "type": "cps"
          },
          {
            "headlines": {
              "headline": "আসছে ট্রাম্পের কেচ্ছা-কাহিনীতে ভরপুর ভাতিজির বই"
            },
            "locators": {
              "assetUri": "/bengali/news-53068313",
              "cpsUrn": "urn:bbc:content:assetUri:bengali/news-53068313",
              "curie": "http://www.bbc.co.uk/asset/8380c385-f177-f240-aa00-94d181476c65",
              "assetId": "53068313"
            },
            "summary": "প্রেসিডেন্ট ট্রাম্পের এক ভাতিজি এক আত্মজীবনী প্রকাশ করতে যাচ্ছেন যেখানে তার পরিবারের ভেতরের নানা ঘটনার খোলামেলা বর্ণনা থাকবে বলে ধারণা করা হচ্ছে।",
            "timestamp": 1592322327000,
            "language": "bn",
            "passport": {
              "category": {
                "categoryId": "http://www.bbc.co.uk/ontologies/applicationlogic-news/News",
                "categoryName": "News"
              },
              "campaigns": [
                {
                  "campaignId": "5a988e4739461b000e9dabfc",
                  "campaignName": "WS - Update me"
                }
              ],
              "taggings": []
            },
            "cpsType": "STY",
            "indexImage": {
              "id": "112923435",
              "subType": "index",
              "href": "http://c.files.bbci.co.uk/D0B8/production/_112923435_gettyimages-1215133825-1.jpg",
              "path": "/cpsprodpb/D0B8/production/_112923435_gettyimages-1215133825-1.jpg",
              "height": 549,
              "width": 976,
              "altText": "স্ত্রী মেলানিয়ার সাথে প্রেসিডেন্ট ট্রাম্প।",
              "caption": "স্ত্রী মেলানিয়ার সাথে প্রেসিডেন্ট ট্রাম্প।",
              "copyrightHolder": "Sarah Silbiger",
              "type": "image"
            },
            "options": {
              "isBreakingNews": false,
              "isFactCheck": false
            },
            "id": "urn:bbc:ares::asset:bengali/news-53068313",
            "type": "cps"
          },
          {
            "headlines": {
              "headline": "দ্বিতীয় মেয়াদে জয়ের জন্য শি জিনপিংয়ের সাহায্য চেয়েছিলেন ট্রাম্প - বোল্টন"
            },
            "locators": {
              "assetUri": "/bengali/news-53088162",
              "cpsUrn": "urn:bbc:content:assetUri:bengali/news-53088162",
              "curie": "http://www.bbc.co.uk/asset/0edfe620-a3f9-264e-8e90-5cc02db75b73",
              "assetId": "53088162"
            },
            "summary": "সাবেক জাতীয় নিরাপত্তা উপদেষ্টা জন বোল্টন নিজের নতুন বইতে এই দাবি করেছেন। ট্রাম্প প্রশাসন ইতিমধ্যেই বইটির প্রকাশনা আটকে দেবার চেষ্টা করছে।",
            "timestamp": 1592449004000,
            "language": "bn",
            "passport": {
              "category": {
                "categoryId": "http://www.bbc.co.uk/ontologies/applicationlogic-news/News",
                "categoryName": "News"
              },
              "campaigns": [
                {
                  "campaignId": "5a988e4739461b000e9dabfc",
                  "campaignName": "WS - Update me"
                }
              ],
              "taggings": []
            },
            "cpsType": "STY",
            "indexImage": {
              "id": "112958556",
              "subType": "index",
              "href": "http://c.files.bbci.co.uk/10031/production/_112958556_1945ad04-d403-43c4-aa94-51d984ac163a.jpg",
              "path": "/cpsprodpb/10031/production/_112958556_1945ad04-d403-43c4-aa94-51d984ac163a.jpg",
              "height": 549,
              "width": 976,
              "altText": "ডোনাল্ড ট্রাম্প",
              "caption": "ডোনাল্ড ট্রাম্প",
              "copyrightHolder": "Getty Images",
              "type": "image"
            },
            "options": {
              "isBreakingNews": false,
              "isFactCheck": false
            },
            "id": "urn:bbc:ares::asset:bengali/news-53088162",
            "type": "cps"
          },
          {
            "headlines": {
              "headline": "প্রাক্তন উপদেষ্টার বই প্রকাশ বন্ধের জন্য ট্রাম্পের আবেদন খারিজ"
            },
            "locators": {
              "assetUri": "/bengali/news-53120742",
              "cpsUrn": "urn:bbc:content:assetUri:bengali/news-53120742",
              "curie": "http://www.bbc.co.uk/asset/20359acc-deba-4eaf-9489-6e5ab1961827",
              "assetId": "53120742"
            },
            "summary": "ডোনাল্ড ট্রাম্পের সাবেক জাতীয় নিরাপত্তা উপদেষ্টা জন বোল্টনের যে বইয়ে প্রেসিডেন্ট সম্পর্কে মারাত্মক সব দাবি রয়েছে তার প্রকাশ আটকের দেওয়ার অনুরোধ প্রত্যাখ্যান করেছেন একজন বিচারক।",
            "timestamp": 1592671922000,
            "language": "bn",
            "passport": {
              "category": {
                "categoryId": "http://www.bbc.co.uk/ontologies/applicationlogic-news/News",
                "categoryName": "News"
              },
              "campaigns": [
                {
                  "campaignId": "5a988e4739461b000e9dabfc",
                  "campaignName": "WS - Update me"
                }
              ],
              "taggings": []
            },
            "cpsType": "STY",
            "indexImage": {
              "id": "113001890",
              "subType": "index",
              "href": "http://c.files.bbci.co.uk/2652/production/_113001890_mediaitem113001888.jpg",
              "path": "/cpsprodpb/2652/production/_113001890_mediaitem113001888.jpg",
              "height": 1152,
              "width": 2048,
              "altText": "জন বোল্টন (ডানে) তাকিয়ে আছেন প্রেসিডেন্ট ট্রাম্পের দিকে - নয়ই মে ২০১৮",
              "caption": "জাতীয় নিরাপত্তা উপদেষ্টা হিসাবে জন বোল্টন আমেরিকার পররাষ্ট্র নীতি বিষয়ে একজন গুরুত্বপূর্ণ ব্যক্তি ছিলেন",
              "copyrightHolder": "AFP",
              "type": "image"
            },
            "options": {
              "isBreakingNews": false,
              "isFactCheck": false
            },
            "id": "urn:bbc:ares::asset:bengali/news-53120742",
            "type": "cps"
          }
        ],
        "semanticGroupName": "Standalone Other Top Stories"
      },
      {
        "type": "feature-digest",
        "title": "Feature Digest",
        "items": [
          {
            "headlines": {
              "headline": "পোস্টাল ভোট: দুই শিবিরেই কারচুপির আশংকা?"
            },
            "locators": {
              "assetUri": "/bengali/news-53891700",
              "cpsUrn": "urn:bbc:content:assetUri:bengali/news-53891700",
              "curie": "http://www.bbc.co.uk/asset/da271aff-9fc7-4c55-ac2b-e091a7da2b13",
              "assetId": "53891700"
            },
            "summary": "ডোনাল্ড ট্রাম্প বলছেন ডেমোক্রাটরা কারচুপি করে প্রেসিডেন্ট নির্বাচন জেতার চেষ্টা করছে। ডেমোক্রাটদের অভিযোগ প্রেসিডেন্ট চুরি করে নির্বাচন জেতার পথ তৈরি করছেন।",
            "timestamp": 1598278413000,
            "language": "bn",
            "passport": {
              "category": {
                "categoryId": "http://www.bbc.co.uk/ontologies/applicationlogic-news/Explainer",
                "categoryName": "Explainer"
              },
              "campaigns": [
                {
                  "campaignId": "5a988e1739461b000e9dabf6",
                  "campaignName": "WS - CS"
                }
              ],
              "taggings": []
            },
            "cpsType": "STY",
            "indexImage": {
              "id": "114029925",
              "subType": "index",
              "href": "http://c.files.bbci.co.uk/CF00/production/_114029925_mediaitem114029924.jpg",
              "path": "/cpsprodpb/CF00/production/_114029925_mediaitem114029924.jpg",
              "height": 549,
              "width": 976,
              "altText": "A US Postal Service worker puts mail in a letter box",
              "copyrightHolder": "EPA",
              "type": "image"
            },
            "options": {
              "isBreakingNews": false,
              "isFactCheck": false
            },
            "id": "urn:bbc:ares::asset:bengali/news-53891700",
            "type": "cps"
          },
          {
            "headlines": {
              "headline": "স্বাস্থ্যসেবায় যুক্তরাষ্ট্রকে কী দিতে চান ডেমোক্র্যাটিক দলের প্রার্থীরা?"
            },
            "locators": {
              "assetUri": "/bengali/news-49684608",
              "cpsUrn": "urn:bbc:content:assetUri:bengali/news-49684608",
              "curie": "http://www.bbc.co.uk/asset/cd488130-dc10-5346-bebe-86ea7de3a86f",
              "assetId": "49684608"
            },
            "summary": "আগামী ২০২০ সালের যুক্তরাষ্টের প্রেসিডেন্ট নির্বাচনে ডেমোক্র্যাটিক পার্টি থেকে মনোনয়ন প্রত্যাশী তিনজন প্রথম সারির নেতা প্রথমবারের মতো একসঙ্গে মঞ্চে এলেন।",
            "timestamp": 1568365767000,
            "language": "bn",
            "passport": {
              "category": {
                "categoryId": "http://www.bbc.co.uk/ontologies/applicationlogic-news/News",
                "categoryName": "News"
              },
              "campaigns": [
                {
                  "campaignId": "5a988e4739461b000e9dabfc",
                  "campaignName": "WS - Update me"
                }
              ],
              "taggings": []
            },
            "cpsType": "STY",
            "indexImage": {
              "id": "108794167",
              "subType": "index",
              "href": "http://c.files.bbci.co.uk/12975/production/_108794167_77188445-2434-431a-8728-f2341dc3100e.jpg",
              "path": "/cpsprodpb/12975/production/_108794167_77188445-2434-431a-8728-f2341dc3100e.jpg",
              "height": 549,
              "width": 976,
              "altText": "বার্নি স্যান্ডার্স (বায়ে), সাবেক মার্কিন সহসভাপতি জো বাইডেন (মাঝে) এবং এলিজাবেথ ওয়ারেন (ডানে)",
              "caption": "ডেমোক্রেটিক প্রেসিডেন্সিয়াল মনোনয়ন প্রত্যাশী বার্নি স্যান্ডার্স (বায়ে), সাবেক মার্কিন সহসভাপতি জো বাইডেন (মাঝে) এবং এলিজাবেথ ওয়ারেন (ডানে)",
              "copyrightHolder": "Getty Images",
              "type": "image"
            },
            "options": {
              "isBreakingNews": false,
              "isFactCheck": false
            },
            "id": "urn:bbc:ares::asset:bengali/news-49684608",
            "type": "cps"
          }
        ],
        "semanticGroupName": "Feature Digest"
      }
    ]
  },
  "promo": {
    "subType": "IDX",
    "name": "যুক্তরাষ্ট্র নির্বাচন ২০২০",
    "uri": "/bengali/53988070",
    "id": "urn:bbc:ares::index:bengali/53988070/desktop/domestic",
    "type": "simple"
  },
  "relatedContent": {
    "section": {
      "subType": "index",
      "name": "খবর, সর্বশেষ খবর, ব্রেকিং নিউজ, বিশ্লেষণ",
      "uri": "/bengali/front_page",
      "type": "simple"
    },
    "site": {
      "subType": "site",
      "name": "খবর, সর্বশেষ খবর, ব্রেকিং নিউজ | News, latest news, breaking news",
      "uri": "/bengali",
      "type": "simple"
    },
    "groups": []
  }
}